minchin.pelican.plugins.nojekyll-1.2.0-py3.11-nspkg.pth
minchin/pelican/plugins/nojekyll.py
minchin.pelican.plugins.nojekyll-1.2.0.dist-info/Licence.txt
minchin.pelican.plugins.nojekyll-1.2.0.dist-info/METADATA
minchin.pelican.plugins.nojekyll-1.2.0.dist-info/WHEEL
minchin.pelican.plugins.nojekyll-1.2.0.dist-info/namespace_packages.txt
minchin.pelican.plugins.nojekyll-1.2.0.dist-info/top_level.txt
minchin.pelican.plugins.nojekyll-1.2.0.dist-info/RECORD
