Metadata-Version: 2.1
Name: minchin.pelican.plugins.nojekyll
Version: 1.2.0
Summary: Pelican plugin that adds a `.nojekyll` file to the output root. Useful for publishing to Github Pages. Written in Python.
Home-page: https://github.com/pelican-plugins/nojekyll
Author: W. Minchin
Author-email: w_minchin@hotmail.com
Classifier: Development Status :: 5 - Production/Stable
Classifier: Environment :: Console
Classifier: Framework :: Pelican :: Plugins
Classifier: License :: OSI Approved :: MIT License
Classifier: Programming Language :: Python
Classifier: Programming Language :: Python :: 3
Classifier: Topic :: Software Development :: Libraries :: Python Modules
License-File: Licence.txt
Requires-Dist: pelican
Requires-Dist: minchin.pelican.plugins.autoloader !=1.2.0
